README.rst
nyanping
ping.py
setup.py
nyanping.egg-info/PKG-INFO
nyanping.egg-info/SOURCES.txt
nyanping.egg-info/dependency_links.txt
nyanping.egg-info/requires.txt
nyanping.egg-info/top_level.txt